gw/__init__.py
gw/lts/__init__.py
gw/lts/em_bright.py
gw/lts/igwn_alert_listener.py
gw/lts/inj_accuracy.py
gw/lts/inj_missed_found.py
gw/lts/inspinjmsg_find.py
gw/lts/latency.py
gw/lts/likelihood.py
gw/lts/p_astro.py
gw/lts/send_inj_stream.py
gw/lts/skymap.py
gw/lts/snr_consistency.py
gw/lts/vt.py
gw/lts/dags/__init__.py
gw/lts/dags/test_suite_workflow.py
gw/lts/utils/__init__.py
gw/lts/utils/cosmology_utils.py
gw/lts/utils/gracedb_helper.py
gw/lts/utils/influx_helper.py
gw/lts/utils/pastro_utils.py
gw_lts-0.5.0.data/data/etc/example_config.yml
gw_lts-0.5.0.data/data/etc/example_fake_data_config.yml
gw_lts-0.5.0.data/data/injections/fake_data_injections.xml.gz
gw_lts-0.5.0.dist-info/LICENSE
gw_lts-0.5.0.dist-info/METADATA
gw_lts-0.5.0.dist-info/WHEEL
gw_lts-0.5.0.dist-info/entry_points.txt
gw_lts-0.5.0.dist-info/top_level.txt
gw_lts-0.5.0.dist-info/RECORD
