Metadata-Version: 2.1
Name: gw-lts
Version: 0.5.0
Summary: Gravitational Wave Low-Latency Test Suite
Home-page: https://git.ligo.org/rebecca.ewing/gw-lts.git
Author: Becca Ewing
Author-email: rebecca.ewing@ligo.org
License: MIT
Classifier: Development Status :: 3 - Alpha
Classifier: Programming Language :: Python
Classifier: Programming Language :: Python :: 3
Classifier: Intended Audience :: Science/Research
Classifier: Natural Language :: English
Requires-Python: >=3.6
License-File: LICENSE
Requires-Dist: confluent-kafka (>=1.7.0)
Requires-Dist: pyyaml
Requires-Dist: htcondor
Requires-Dist: htcondor-dags
Requires-Dist: python-ligo-lw (>=1.8.0)
Requires-Dist: lalsuite (>=6.82)
Requires-Dist: cronut (>=0.1.0)
Requires-Dist: ligo-scald (>=0.8.4)
Requires-Dist: ligo.skymap
Requires-Dist: igwn-alert (>=0.2.2)
Requires-Dist: hop-client (>=0.6.0)
Requires-Dist: poetry
Requires-Dist: ligo.em-bright
Provides-Extra: docs
Requires-Dist: mkdocs (>=1.3) ; extra == 'docs'
Requires-Dist: mkdocs-coverage (>=0.2) ; extra == 'docs'
Requires-Dist: mkdocs-gen-files (>=0.3) ; extra == 'docs'
Requires-Dist: mkdocs-literate-nav (>=0.4) ; extra == 'docs'
Requires-Dist: mkdocs-material-igwn ; extra == 'docs'
Requires-Dist: mkdocs-section-index (>=0.3) ; extra == 'docs'
Requires-Dist: mkdocstrings[python] ; extra == 'docs'
Requires-Dist: markdown-callouts (>=0.2) ; extra == 'docs'
Requires-Dist: markdown-exec (>=0.5) ; extra == 'docs'
Requires-Dist: toml (>=0.10) ; extra == 'docs'
